test_anton.py
test_anton-1.5.0.dist-info/WHEEL
test_anton-1.5.0.dist-info/METADATA
test_anton-1.5.0.dist-info/RECORD
