Metadata-Version: 2.1
Name: test-anton
Version: 1.5.0
Summary: it is mini desc
License: @copiripe anton skazko liciense
Author: Skazko Anton
Author-email: sk.anton06@gmail.com
Requires-Python: >=3.7,<4.0
Classifier: License :: Other/Proprietary License
Classifier: Programming Language :: Python :: 3
Classifier: Programming Language :: Python :: 3.10
Classifier: Programming Language :: Python :: 3.7
Classifier: Programming Language :: Python :: 3.8
Classifier: Programming Language :: Python :: 3.9
